arwcom/__init__.py
arwcom/__main__.py
arwcom/client/__init__.py
arwcom/client/client.py
arwcom/combaseapi.py
arwcom/guiddef.py
arwcom/iunknown.py
arwcom/wintypesbase.py
arwcom-0.1.0.dist-info/LICENSE
arwcom-0.1.0.dist-info/WHEEL
arwcom-0.1.0.dist-info/METADATA
arwcom-0.1.0.dist-info/RECORD
