Metadata-Version: 2.1
Name: arwcom
Version: 0.1.0
Summary: Lightweight Python 3 API to access Windows COM Objects
License: MIT
Author: alwinw
Author-email: 16846521+alwinw@users.noreply.github.com
Requires-Python: >=3.7,<4.0
Classifier: License :: OSI Approved :: MIT License
Classifier: Programming Language :: Python :: 3
Classifier: Programming Language :: Python :: 3.10
Classifier: Programming Language :: Python :: 3.7
Classifier: Programming Language :: Python :: 3.8
Classifier: Programming Language :: Python :: 3.9
